{
  "_class": "shapeGroup",
  "booleanOperation": 0,
  "clippingMaskMode": 0,
  "do_objectID": "6A3CDACB-8E2B-443D-9AD1-C4474D5A5091",
  "exportOptions": {
    "_class": "exportOptions",
    "exportFormats": [
    ],
    "includedLayerIds": [
    ],
    "layerOptions": 0,
    "shouldTrim": false
  },
  "frame": {
    "_class": "rect",
    "constrainProportions": false,
    "height": 22,
    "width": 22,
    "x": 1,
    "y": 1
  },
  "groupLayout": {
    "_class": "MSImmutableFreeformGroupLayout"
  },
  "hasClickThrough": false,
  "hasClippingMask": true,
  "isFixedToViewport": false,
  "isFlippedHorizontal": false,
  "isFlippedVertical": false,
  "isLocked": false,
  "isVisible": true,
  "layerListExpandedType": 0,
  "layers": [
    {
      "class": "shapePath",
      "id": "1F4FFEEC-3FBD-4A55-8167-27727C81C64A"
    },
    {
      "class": "shapePath",
      "id": "7DBC22DD-8A72-475E-B8FD-E262FAD9A64C"
    },
    {
      "class": "shapePath",
      "id": "FEA8B382-BA7E-4D28-B980-13FD262CB413"
    }
  ],
  "name": "Shape",
  "nameIsFixed": false,
  "resizingConstraint": 63,
  "resizingType": 0,
  "rotation": 0,
  "sharedStyleID": "C378BDDA-ED40-460E-AC15-4BC1B48D3822",
  "shouldBreakMaskChain": false,
  "style": {
    "_class": "style",
    "do_objectID": "B82D7E63-4CBD-4793-95DF-71F50437CEFF",
    "endMarkerType": 0,
    "fills": [
      {
        "_class": "fill",
        "color": {
          "_class": "color",
          "alpha": 1,
          "blue": 0.1704879981884058,
          "green": 0.1704879981884058,
          "red": 0.1704879981884058
        },
        "fillType": 0,
        "isEnabled": true,
        "noiseIndex": 0,
        "noiseIntensity": 0,
        "patternFillType": 1,
        "patternTileScale": 1
      }
    ],
    "miterLimit": 10,
    "startMarkerType": 0,
    "windingRule": 0
  },
  "windingRule": 0
}