{
  "_class": "shapePath",
  "booleanOperation": 0,
  "clippingMaskMode": 0,
  "do_objectID": "59A98A42-E083-4362-8190-EE66EA095E84",
  "edited": true,
  "exportOptions": {
    "_class": "exportOptions",
    "do_objectID": "1F8CFC85-3705-4BBD-A5C2-71C24A1CD9E3",
    "exportFormats": [
    ],
    "includedLayerIds": [
    ],
    "layerOptions": 0,
    "shouldTrim": false
  },
  "frame": {
    "_class": "rect",
    "constrainProportions": false,
    "do_objectID": "6A5A3769-ED15-4F68-BD42-84968F1201B0",
    "height": 2.999999999999963,
    "width": 5.999999999999331,
    "x": 4.000000000000213,
    "y": 12.00000000000002
  },
  "hasClippingMask": false,
  "isClosed": false,
  "isFixedToViewport": false,
  "isFlippedHorizontal": false,
  "isFlippedVertical": true,
  "isLocked": false,
  "isVisible": true,
  "layerListExpandedType": 0,
  "name": "Path",
  "nameIsFixed": false,
  "pointRadiusBehaviour": 1,
  "points": [
    {
      "_class": "curvePoint",
      "cornerRadius": 0,
      "curveFrom": "{0, 1}",
      "curveMode": 1,
      "curveTo": "{0, 1}",
      "hasCurveFrom": false,
      "hasCurveTo": false,
      "point": "{0, 1}"
    },
    {
      "_class": "curvePoint",
      "cornerRadius": 0,
      "curveFrom": "{0.5000000000000161, 0}",
      "curveMode": 1,
      "curveTo": "{0.5000000000000161, 0}",
      "hasCurveFrom": false,
      "hasCurveTo": false,
      "point": "{0.5000000000000161, 0}"
    },
    {
      "_class": "curvePoint",
      "cornerRadius": 0,
      "curveFrom": "{1, 1}",
      "curveMode": 1,
      "curveTo": "{1, 1}",
      "hasCurveFrom": false,
      "hasCurveTo": false,
      "point": "{1, 1}"
    }
  ],
  "resizingConstraint": 63,
  "resizingType": 0,
  "rotation": 0,
  "shouldBreakMaskChain": false,
  "style": {
    "_class": "style",
    "borderOptions": {
      "_class": "borderOptions",
      "dashPattern": [
      ],
      "do_objectID": "703A264D-D9C7-4808-8F08-E3AB8FE1DF3D",
      "isEnabled": false,
      "lineCapStyle": 1,
      "lineJoinStyle": 1
    },
    "borders": [
      {
        "_class": "border",
        "color": {
          "_class": "color",
          "alpha": 1,
          "blue": 0.7307518115942029,
          "green": 0.7307518115942029,
          "red": 0.7307518115942029
        },
        "fillType": 0,
        "isEnabled": true,
        "position": 0,
        "thickness": 2
      }
    ],
    "do_objectID": "D3F816B5-E92B-421E-B58E-983ECD27082E",
    "endMarkerType": 0,
    "miterLimit": 10,
    "startMarkerType": 0,
    "windingRule": 1
  }
}