{
  "_class": "shapePath",
  "booleanOperation": -1,
  "clippingMaskMode": 0,
  "do_objectID": "B24156D3-A25D-40E7-ADB4-06B184AD206A",
  "edited": true,
  "exportOptions": {
    "_class": "exportOptions",
    "exportFormats": [
    ],
    "includedLayerIds": [
    ],
    "layerOptions": 0,
    "shouldTrim": false
  },
  "frame": {
    "_class": "rect",
    "constrainProportions": false,
    "height": 3.400000000000002,
    "width": 3.400000000000001,
    "x": 3.200000000000001,
    "y": 8.2
  },
  "hasClippingMask": false,
  "isClosed": true,
  "isFixedToViewport": false,
  "isFlippedHorizontal": false,
  "isFlippedVertical": false,
  "isLocked": false,
  "isVisible": true,
  "layerListExpandedType": 1,
  "name": "Path",
  "nameIsFixed": false,
  "pointRadiusBehaviour": 1,
  "points": [
    {
      "_class": "curvePoint",
      "cornerRadius": 0,
      "curveFrom": "{0.5588235294117645, 0.9705882352941172}",
      "curveMode": 4,
      "curveTo": "{0.49999999999999978, 0.91176470588235281}",
      "hasCurveFrom": true,
      "hasCurveTo": false,
      "point": "{0.49999999999999978, 0.91176470588235281}"
    },
    {
      "_class": "curvePoint",
      "cornerRadius": 0,
      "curveFrom": "{0.76470588235294101, 1}",
      "curveMode": 2,
      "curveTo": "{0.64705882352941158, 1}",
      "hasCurveFrom": true,
      "hasCurveTo": true,
      "point": "{0.70588235294117629, 1}"
    },
    {
      "_class": "curvePoint",
      "cornerRadius": 0,
      "curveFrom": "{1.0294117647058822, 0.79411764705882337}",
      "curveMode": 3,
      "curveTo": "{0.85294117647058798, 0.97058823529411775}",
      "hasCurveFrom": true,
      "hasCurveTo": true,
      "point": "{0.9117647058823527, 0.91176470588235281}"
    },
    {
      "_class": "curvePoint",
      "cornerRadius": 0,
      "curveFrom": "{0.9117647058823527, 0.5}",
      "curveMode": 4,
      "curveTo": "{1.0294117647058822, 0.61764705882352944}",
      "hasCurveFrom": false,
      "hasCurveTo": true,
      "point": "{0.9117647058823527, 0.5}"
    },
    {
      "_class": "curvePoint",
      "cornerRadius": 0,
      "curveFrom": "{0.38235294117647034, -0.029411764705882231}",
      "curveMode": 4,
      "curveTo": "{0.49999999999999978, 0.088235294117647217}",
      "hasCurveFrom": true,
      "hasCurveTo": false,
      "point": "{0.49999999999999978, 0.088235294117647217}"
    },
    {
      "_class": "curvePoint",
      "cornerRadius": 0,
      "curveFrom": "{-0.029411764705882373, 0.20588235294117666}",
      "curveMode": 2,
      "curveTo": "{0.20588235294117635, -0.029411764705882231}",
      "hasCurveFrom": true,
      "hasCurveTo": true,
      "point": "{0.088235294117646981, 0.088235294117647217}"
    },
    {
      "_class": "curvePoint",
      "cornerRadius": 0,
      "curveFrom": "{0.088235294117646981, 0.5}",
      "curveMode": 4,
      "curveTo": "{-0.029411764705882373, 0.38235294117647056}",
      "hasCurveFrom": false,
      "hasCurveTo": true,
      "point": "{0.088235294117646981, 0.5}"
    }
  ],
  "resizingConstraint": 63,
  "resizingType": 0,
  "rotation": 0,
  "shouldBreakMaskChain": false,
  "style": {
    "_class": "style",
    "endMarkerType": 0,
    "fills": [
      {
        "_class": "fill",
        "color": {
          "_class": "color",
          "alpha": 1,
          "blue": 0,
          "green": 0,
          "red": 0
        },
        "fillType": 0,
        "isEnabled": true,
        "noiseIndex": 0,
        "noiseIntensity": 0,
        "patternFillType": 1,
        "patternTileScale": 1
      }
    ],
    "miterLimit": 10,
    "startMarkerType": 0,
    "windingRule": 0
  }
}