{
  "_class": "group",
  "booleanOperation": -1,
  "clippingMaskMode": 0,
  "do_objectID": "33CD40CF-88DD-44DF-B16B-EA58F255BED6",
  "exportOptions": {
    "_class": "exportOptions",
    "exportFormats": [
    ],
    "includedLayerIds": [
    ],
    "layerOptions": 0,
    "shouldTrim": false
  },
  "frame": {
    "_class": "rect",
    "constrainProportions": false,
    "height": 204,
    "width": 328,
    "x": 0,
    "y": 440
  },
  "groupLayout": {
    "_class": "MSImmutableFreeformGroupLayout"
  },
  "hasClickThrough": false,
  "hasClippingMask": false,
  "isFixedToViewport": false,
  "isFlippedHorizontal": false,
  "isFlippedVertical": false,
  "isLocked": false,
  "isVisible": true,
  "layerListExpandedType": 0,
  "layers": [
    {
      "class": "rectangle",
      "id": "1933ECDD-B1EF-4BD2-B4B5-06E098C7AE46"
    },
    {
      "class": "rectangle",
      "id": "A5C23EEB-5AB7-43F1-883C-0EF262BEA687"
    },
    {
      "class": "rectangle",
      "id": "BEEB1E12-2CE1-4DA1-9A5B-6A990FF74A90"
    }
  ],
  "name": "Group 2",
  "nameIsFixed": false,
  "resizingConstraint": 63,
  "resizingType": 0,
  "rotation": 0,
  "shouldBreakMaskChain": false,
  "style": {
    "_class": "style",
    "endMarkerType": 0,
    "miterLimit": 10,
    "startMarkerType": 0,
    "windingRule": 1
  }
}