{
  "_class": "shapePath",
  "booleanOperation": -1,
  "clippingMaskMode": 0,
  "do_objectID": "E999C2E4-448B-4D5E-B0E6-7DB78804A754",
  "edited": true,
  "exportOptions": {
    "_class": "exportOptions",
    "exportFormats": [
    ],
    "includedLayerIds": [
    ],
    "layerOptions": 0,
    "shouldTrim": false
  },
  "frame": {
    "_class": "rect",
    "constrainProportions": false,
    "height": 10,
    "width": 10,
    "x": 7,
    "y": 7
  },
  "hasClippingMask": false,
  "isClosed": true,
  "isFixedToViewport": false,
  "isFlippedHorizontal": false,
  "isFlippedVertical": false,
  "isLocked": false,
  "isVisible": true,
  "layerListExpandedType": 1,
  "name": "Path",
  "nameIsFixed": false,
  "pointRadiusBehaviour": 1,
  "points": [
    {
      "_class": "curvePoint",
      "cornerRadius": 0,
      "curveFrom": "{0.040000000000000036, 1}",
      "curveMode": 4,
      "curveTo": "{0.10000000000000001, 1}",
      "hasCurveFrom": true,
      "hasCurveTo": false,
      "point": "{0.10000000000000001, 1}"
    },
    {
      "_class": "curvePoint",
      "cornerRadius": 0,
      "curveFrom": "{0, 0.90000000000000002}",
      "curveMode": 4,
      "curveTo": "{0, 0.96000000000000019}",
      "hasCurveFrom": false,
      "hasCurveTo": true,
      "point": "{0, 0.90000000000000002}"
    },
    {
      "_class": "curvePoint",
      "cornerRadius": 0,
      "curveFrom": "{0.0099999999999999638, 0.0099999999999999638}",
      "curveMode": 1,
      "curveTo": "{0.0099999999999999638, 0.0099999999999999638}",
      "hasCurveFrom": false,
      "hasCurveTo": false,
      "point": "{0.0099999999999999638, 0.0099999999999999638}"
    },
    {
      "_class": "curvePoint",
      "cornerRadius": 0,
      "curveFrom": "{0.96000000000000019, 0}",
      "curveMode": 4,
      "curveTo": "{0.90000000000000002, 0}",
      "hasCurveFrom": true,
      "hasCurveTo": false,
      "point": "{0.90000000000000002, 0}"
    },
    {
      "_class": "curvePoint",
      "cornerRadius": 0,
      "curveFrom": "{1, 0.10000000000000001}",
      "curveMode": 4,
      "curveTo": "{1, 0.040000000000000036}",
      "hasCurveFrom": false,
      "hasCurveTo": true,
      "point": "{1, 0.10000000000000001}"
    },
    {
      "_class": "curvePoint",
      "cornerRadius": 0,
      "curveFrom": "{1, 1}",
      "curveMode": 1,
      "curveTo": "{1, 1}",
      "hasCurveFrom": false,
      "hasCurveTo": false,
      "point": "{1, 1}"
    }
  ],
  "resizingConstraint": 63,
  "resizingType": 0,
  "rotation": 0,
  "shouldBreakMaskChain": false,
  "style": {
    "_class": "style",
    "endMarkerType": 0,
    "fills": [
      {
        "_class": "fill",
        "color": {
          "_class": "color",
          "alpha": 1,
          "blue": 0,
          "green": 0,
          "red": 0
        },
        "fillType": 0,
        "isEnabled": true,
        "noiseIndex": 0,
        "noiseIntensity": 0,
        "patternFillType": 1,
        "patternTileScale": 1
      }
    ],
    "miterLimit": 10,
    "startMarkerType": 0,
    "windingRule": 0
  }
}