{
  "_class": "group",
  "booleanOperation": -1,
  "clippingMaskMode": 0,
  "do_objectID": "8A55A03C-9D35-4204-BDA8-A828EA00AC13",
  "exportOptions": {
    "_class": "exportOptions",
    "do_objectID": "65C38E3C-8DA2-40B4-8645-E4F0EE33E48B",
    "exportFormats": [
    ],
    "includedLayerIds": [
    ],
    "layerOptions": 0,
    "shouldTrim": false
  },
  "frame": {
    "_class": "rect",
    "constrainProportions": false,
    "do_objectID": "B9E2CF8F-3B1D-4648-924B-BD1B3F055BAE",
    "height": 148,
    "width": 316,
    "x": 22,
    "y": 225
  },
  "groupLayout": {
    "_class": "MSImmutableFreeformGroupLayout",
    "do_objectID": "5CE85B4A-BAE2-4FA3-B6E7-9C45C3F6C1F5"
  },
  "hasClickThrough": false,
  "hasClippingMask": false,
  "isFixedToViewport": false,
  "isFlippedHorizontal": false,
  "isFlippedVertical": false,
  "isLocked": false,
  "isVisible": true,
  "layerListExpandedType": 0,
  "layers": [
    {
      "class": "group",
      "id": "2DF206A2-4C43-4398-BA1C-DC251587EAE9"
    },
    {
      "class": "group",
      "id": "0E159ED6-6785-4C5A-823A-90C52093772B"
    }
  ],
  "name": "micro app",
  "nameIsFixed": true,
  "resizingConstraint": 63,
  "resizingType": 0,
  "rotation": 0,
  "shouldBreakMaskChain": false,
  "style": {
    "_class": "style",
    "do_objectID": "57894EFE-0CD3-407B-8620-00587C54B028",
    "endMarkerType": 0,
    "miterLimit": 10,
    "startMarkerType": 0,
    "windingRule": 1
  },
  "userInfo": {
    "com.animaapp.stc-sketch-plugin": {
      "kModelPropertiesKey": {
        "align": 0,
        "isCollapsing": 1,
        "resizesContainer": 1,
        "spacing": 20,
        "stackType": 0
      },
      "kViewTypeKey": "ADModelStackView"
    }
  }
}